{
    "engine.cef.subprocessdied.msg": "Proces používateľského rozhrania neodpovedal včas.\nMôže to byť spôsobené antivírusovým programom, ktorý blokuje aplikáciu BeamNG.drive.ui.exe.\n\nViac informácií nájdete tu:\n\nhttp://wiki.beamng.com/Errors/Unresponsive_UI_Process\n\nChcete teraz prejsť na túto adresu?",
    "engine.cef.subprocessdied.title": "UI proces neodpovedá",
    "engine.cef.subprocessdied.url": "http://wiki.beamng.com/Errors/Unresponsive_UI_Process",
    "engine.editor.menu.createBlankTerrain": "Vytvoriť prázdny terén",
    "engine.editor.menu.exitLevel": "Opustiť úroveň",
    "engine.editor.menu.exportTerrainHeightmap": "Exportovať výškovú mapu terénu",
    "engine.editor.menu.exportToCollada": "Exportovať do COLLADA...",
    "engine.editor.menu.file": "Súbor",
    "engine.editor.menu.importTerrainHeightmap": "Importovať výškovú mapu terénu",
    "engine.editor.menu.newLevel": "Nová úroveň",
    "engine.editor.menu.openLevel": "Otvoriť úroveň...",
    "engine.editor.menu.playLevel": "Hrať úroveň",
    "engine.editor.menu.quit": "Opustiť hru",
    "engine.editor.menu.saveLevel": "Uložiť úroveň",
    "engine.editor.menu.saveLevelAs": "Uložiť úroveň ako...",
    "engine.engineFail": "Nepodarilo sa inicializovať hru, vypínam.",
    "engine.invalidUserpath.msg": "BeamNG.drive sa nemôže dostať k UserPath definovanej v startup.ini (priečinok hry). Zmeňte ju na platnú cestu: ",
    "engine.invalidUserpath.title": "Nesprávna používateľská cesta",
    "engine.levelModified.msg": "Úroveň bola zmenená editorom. Uložiť?",
    "engine.levelModified.title": "Úroveň upravená",
    "engine.msgboxErrorTitle": "Chyba",
    "engine.resourceMissing": "Chyba pri tvorbe dát (nechýba súbor?): ",
    "engine.welcome": "Vitajte v BeamNG.drive v americkej angličtine :)",
    "engine.windowedModeReq.msgEditor": "Prosím opusťte editor misií pre prepnutie do režimu celej obrazovky.",
    "engine.windowedModeReq.msgGUI": "Prosím opusťte grafické používateľské rozhranie pre prepnutie do režimu celej obrazovky.",
    "engine.windowedModeReq.title": "Režim v okne vyžadovaný",
    "ui.apps.vehicleDebug.breakAll": "Zničiť všetky zničiteľné skupiny",
    "ui.apps.vehicleDebug.breakHinges": "Zničiť všetky pánty",
    "ui.apps.vehicleDebug.deflateTires": "Vypustiť vzduch z pneumatík",
    "ui.apps.vehicleDebug.explodeVehicle": "Explodovať vozidlo",
    "ui.apps.vehicleDebug.extinguishVehicle": "Uhasiť vozidlo",
    "ui.apps.vehicleDebug.igniteNode": "Zapáliť Uzol",
    "ui.apps.vehicleDebug.igniteNodeMin": "Slabo podpáliť uzol",
    "ui.apps.vehicleDebug.igniteVehicle": "Podpáliť vozidlo",
    "ui.appselect.add": "Pridať aplikáciu",
    "ui.appselect.apps": "Aplikácie",
    "ui.appselect.deselectAll": "Zrušiť všetok výber",
    "ui.appselect.done": "Hotovo",
    "ui.appselect.downloadMore": "Stiahnuť viac!",
    "ui.appselect.filters": "Filtre",
    "ui.appselect.official": "Oficiálny",
    "ui.appselect.reset": "Reštartovať rozmiestnenie",
    "ui.appselect.search": "Hľadanie",
    "ui.appselect.selectAll": "Zvoliť všetko",
    "ui.colorpicker.brightness": "Jas",
    "ui.colorpicker.chrominess": "Chrómovosť",
    "ui.colorpicker.colToPre": "Pridať farbu do predvolieb",
    "ui.colorpicker.color": "Farba",
    "ui.colorpicker.rightToDel": "Pravým kliknutím zmažete predvoľbu",
    "ui.colorpicker.saturation": "Saturácia",
    "ui.colorpicker.userPresets": "Predvoľby používateľa",
    "ui.credits.assistantenvArtists": "Pomocný výtvarníci prostredia",
    "ui.credits.conceptArtists2D": "Konceptoví výtvarníci - 2D",
    "ui.credits.customerSupport": "Zákaznícka podpora",
    "ui.credits.environmentArtists": "Výtvarníci prostredia",
    "ui.credits.madePossibleWith": "Bolo možné uskutočniť vďaka",
    "ui.credits.organization": "Organizácia",
    "ui.credits.ourAwesomeCommunity": "Naša úžasná komunita",
    "ui.credits.programmers": "Programátori",
    "ui.credits.qa": "Kontrola kvality",
    "ui.credits.sound": "Zvuk",
    "ui.credits.specialThanksTo": "Zvláštne poďakovanie",
    "ui.credits.sysops": "Systémové operácie",
    "ui.credits.ui": "Používateľské rozhranie",
    "ui.credits.vehicleDesigners": "Výtvarníci vozidiel",
    "ui.dashboard.apps": "Aplikácie",
    "ui.dashboard.audiodebug": "Ladenie audia",
    "ui.dashboard.controls": "Ovládanie",
    "ui.dashboard.credits": "Titulky",
    "ui.dashboard.debug": "Ladenie",
    "ui.dashboard.drive": "Jazdiť",
    "ui.dashboard.environment": "Prostredie",
    "ui.dashboard.feedback": "Spätná väzba",
    "ui.dashboard.garagePartselect": "Nový výber dielov",
    "ui.dashboard.help": "Pomoc",
    "ui.dashboard.levels": "Úrovne",
    "ui.dashboard.mainmenu": "Hlavné menu",
    "ui.dashboard.mods": "Mody",
    "ui.dashboard.options": "Nastavenia",
    "ui.dashboard.performance": "Výkon",
    "ui.dashboard.photomode": "Fotografický režim",
    "ui.dashboard.play": "Hrať",
    "ui.dashboard.quit": "Ukončiť hru",
    "ui.dashboard.scenarios": "Misie",
    "ui.dashboard.tutorial": "Tutoriál",
    "ui.dashboard.vehicleconfig": "Konfigurácia vozidiel",
    "ui.dashboard.vehicles": "Vozidlá",
    "ui.environment.cloudCover": "Oblačnosť",
    "ui.environment.day": "Ďeň",
    "ui.environment.earth": "Zem",
    "ui.environment.environment": "Prostredie",
    "ui.environment.fogDensity": "Hustota hmly",
    "ui.environment.gravity": "Gravitácia",
    "ui.environment.jupiter": "Jupiter",
    "ui.environment.mars": "Mars",
    "ui.environment.mercury": "Merkúr",
    "ui.environment.moon": "Mesiac",
    "ui.environment.negativeEarth": "Záporná Zem",
    "ui.environment.neptune": "Neptún",
    "ui.environment.night": "Noc",
    "ui.environment.play": "Spustiť",
    "ui.environment.pluto": "Pluto",
    "ui.environment.realtime": "Reálny čas",
    "ui.environment.saturn": "Saturn",
    "ui.environment.scale": "Mierka",
    "ui.environment.simulationSpeed": "Rýchlosť simulácie",
    "ui.environment.sun": "Slnko",
    "ui.environment.time": "Čas",
    "ui.environment.timeOfDay": "Čas dňa",
    "ui.environment.uranus": "Urán",
    "ui.environment.venus": "Venuša",
    "ui.environment.weather": "Počasie",
    "ui.environment.windSpeed": "Rýchlosť vetra",
    "ui.environment.zeroGravity": "Nulová gravitácia",
    "ui.feedback.back": "Späť",
    "ui.feedback.clear": "Vymazať",
    "ui.feedback.leaveMessage": "Pridajte sem správu prosím",
    "ui.feedback.submit": "Odoslať",
    "ui.launcher.test": "Ahoj svet!",
    "ui.levelselect.authors": "Autor(i)",
    "ui.levelselect.biome": "Bióm",
    "ui.levelselect.chooseSpwanpoint": "Zvoľte predvolenú pozíciu",
    "ui.levelselect.description": "Popis",
    "ui.levelselect.features": "Funkcie",
    "ui.levelselect.play": "Hrať",
    "ui.levelselect.roads": "Cesty",
    "ui.levelselect.size": "Veľkosť",
    "ui.levelselect.spawn": "Začiatočná pozícia",
    "ui.levelselect.spawnpoints": "Začiatočné miesta",
    "ui.levelselect.suitablefor": "Vhodné pre",
    "ui.levelselect.title": "Volná jazda",
    "ui.mainmenu.credits": "TITULKY",
    "ui.mainmenu.exit": "KONIEC",
    "ui.mainmenu.garage": "GARÁŽ",
    "ui.mainmenu.help": "POMOC",
    "ui.mainmenu.mods": "MODY",
    "ui.mainmenu.news": "NOVINKY",
    "ui.mainmenu.options": "NASTAVENIA",
    "ui.mainmenu.play": "HRAŤ",
    "ui.mainmenu.repo": "Repozitár",
    "ui.modmanager.modmanager": "Správca modov",
    "ui.options.audio": "Zvuk",
    "ui.options.gameplay": "Hrateľnosť",
    "ui.options.graphics": "Grafika",
    "ui.options.graphics.GraphicDynReflection": "Dynamický odraz",
    "ui.options.graphics.GraphicDynReflection.warning": "Pozor - počet odrazových štvorcov za jednu aktualizáciu dokáže byť veľmi graficky náročný. Ak spozorujete problémy, uvažujte nad znížením tohto nastavenia",
    "ui.options.graphics.GraphicDynReflectionDetail": "Detail",
    "ui.options.graphics.GraphicDynReflectionDistance": "Vzdialenosť",
    "ui.options.graphics.GraphicDynReflectionFacesPerupdate": "Počet odrazových plôch za aktualizáciu",
    "ui.options.graphics.GraphicDynReflectionTexsize": "Veľkosť textúry",
    "ui.options.graphics.antialiasing": "Vyhladzovanie hrán",
    "ui.options.graphics.borderless": "Bezrámový",
    "ui.options.graphics.display": "Obraz",
    "ui.options.graphics.fpslimiter": "Obmedzovač FPS",
    "ui.options.graphics.fullscreen": "Celá obrazovka",
    "ui.options.graphics.gamma": "Gamma korekcia",
    "ui.options.graphics.grassdensity": "Hustota trávy",
    "ui.options.graphics.overallquality": "Celková kvalita obrazu",
    "ui.options.graphics.resolution": "Rozlíšenie",
    "ui.options.graphics.uimaxres": "Maximálne rozlíšenie používateľského rozhrania",
    "ui.options.graphics.vsync": "Vertikálna synchronizácia",
    "ui.options.options": "Nastavenia",
    "ui.photomode.advancedImgSettings": "Pokročilé nastavenia obrazu",
    "ui.photomode.blureCurveFar": "Krivka rozmazania do diaľky",
    "ui.photomode.cameraSpeed": "Rýchlosť kamery",
    "ui.photomode.farBlurMax": "Maximálne ďaleké rozmazanie",
    "ui.photomode.focusRangeMax": "Rozsah zaostrenia (Max)",
    "ui.photomode.focusRangeMin": "Rozsah zaostrenia (Min)",
    "ui.photomode.fov": "Zorné pole",
    "ui.photomode.postfx": "PostFX",
    "ui.photomode.quitPhotoMode": "Zrušiť photo mód",
    "ui.photomode.roll": "Náklon",
    "ui.photomode.showGrid": "Zobraziť mriežku",
    "ui.photomode.takeScreen": "Vytvoriť snímok obrazovky",
    "ui.photomode.takebigScreen": "Vytvoriť veľký snímok obrazovky",
    "ui.photomode.uploadScreen": "Nahrať obrázok na media server",
    "ui.playmodes.campaigns": "Kampane",
    "ui.playmodes.career": "Kariéra",
    "ui.playmodes.comingSoon": "Už čoskoro",
    "ui.playmodes.freeroam": "Volná jazda",
    "ui.playmodes.scenarios": "Misie",
    "ui.vehicleconfig.color": "Farba",
    "ui.vehicleconfig.filename": "Názov súboru",
    "ui.vehicleconfig.load": "Načítať",
    "ui.vehicleconfig.mouseOverUi": "Prosím ponechajte myš nad používateľským rozhraním počas písania, aby bolo možné zachytávať stláčanie kláves",
    "ui.vehicleconfig.overwrite": "Prepísať",
    "ui.vehicleconfig.parts": "Súčiastky",
    "ui.vehicleconfig.save": "Uložiť",
    "ui.vehicleconfig.tuning": "Ladenie vozidla",
    "ui.vehicleconfig.vehicleconfig": "Úprava vozidiel"
}
